<?xml version="1.0" encoding="utf-8"?>
<odoo>
    <record id="ir_cron_product_price_by_pricelist" model="ir.cron">
        <field name="name">Put price unit by pricelist in products</field>
        <field name="interval_number">1</field>
        <field name="interval_type">days</field>
        <field name="numbercall">-1</field>
        <field name="doall" eval="False"/>
        <field name="model_id" ref="model_product_product"/>
        <field name="code">model.put_price_unit_by_pricelist_in_products()</field>
        <field name="state">code</field>
    </record>
</odoo>
