<?xml version="1.0" encoding="UTF-8"?>
<odoo>
    <record id="email_template_form" model="ir.ui.view">
        <field name="model">mail.template</field>
        <field name="inherit_id" ref="mail.email_template_form" />
        <field name="arch" type="xml">
            <field name="model_id" position="after">
                <field name="company_id"/>
            </field>
        </field>
    </record>
    <record id="email_template_tree" model="ir.ui.view">
        <field name="model">mail.template</field>
        <field name="inherit_id" ref="mail.email_template_tree" />
        <field name="arch" type="xml">
            <field name="model_id" position="after">
                <field name="company_id" />
            </field>
        </field>
    </record>
</odoo>
